{"A11001":"八德路４段","A11002":"三重路","A11003":"中坡北路","A11004":"中坡南路","A11005":"中南街","A11006":"市民大道７段","A11007":"市民大道８段","A11008":"永吉路","A11009":"玉成街","A11010":"同德路","A11011":"向陽路","A11012":"合順街","A11013":"成功路１段","A11014":"成福路","A11015":"忠孝東路５段","A11016":"忠孝東路６段","A11017":"忠孝東路７段","A11018":"昆陽街","A11019":"東明街","A11020":"東南街","A11021":"東新街","A11022":"松河街","A11023":"南深路","A11024":"南港路１段","A11025":"南港路２段","A11026":"南港路３段","A11027":"研究院路１段","A11028":"研究院路２段","A11029":"研究院路３段","A11030":"研究院路４段","A11031":"重陽路","A11032":"富康街","A11033":"惠民街","A11034":"港東街","A11035":"園區街","A11036":"新民街","A11037":"經貿一路","A11038":"經貿二路","A11039":"經園街","A11040":"福山街","A11041":"福德街","A11042":"興中路","A11043":"興東街","A11044":"興南街","A11045":"興華路","A11046":"舊莊街１段","A11047":"舊莊街２段"}