{"F06001":"三民路","F06002":"下山","F06003":"上山","F06004":"大華路","F06005":"山豬湖","F06006":"中坑","F06007":"五和街","F06008":"五股林","F06009":"五座屋","F06010":"文山路","F06011":"文仁街","F06012":"文化街","F06013":"文孝街","F06014":"文忠街","F06015":"文昌街","F06016":"文昌街廣福巷","F06017":"文明路","F06018":"文華街","F06019":"文福街","F06020":"文德路","F06021":"文衡路","F06022":"水坑","F06023":"王爺坑","F06024":"石壁潭","F06025":"光明街","F06026":"光復一街","F06027":"光復二街","F06028":"光復街","F06029":"竹林路","F06030":"赤柯寮","F06031":"柯子林","F06032":"倒別牛","F06033":"崁下","F06034":"紙寮窩","F06035":"鹿寮坑","F06036":"富林路１段","F06037":"富林路２段","F06038":"富林路３段","F06039":"嘉慶","F06040":"福昌街","F06041":"燥坑"}