{"H13001":"一心路","H13002":"三民路","H13003":"三村路","H13004":"三村路仁德屯","H13005":"三村路合作新村","H13006":"三角路","H13007":"三和路","H13008":"三環路","H13009":"三豐路","H13010":"大仁街","H13011":"大光街","H13012":"大昌街","H13013":"大明路","H13014":"大社街","H13015":"大勇街","H13016":"大順街","H13017":"大湳街","H13018":"大豐路５段","H13019":"中山路","H13020":"中正路","H13021":"中陽東街","H13022":"中陽路","H13023":"中興路","H13024":"中興路今日市場","H13025":"互助街","H13026":"仁洲街","H13027":"仁愛街","H13028":"文化街","H13029":"文村街","H13030":"文昌西街","H13031":"文昌東街","H13032":"文昌街","H13033":"文賢街","H13034":"水源路","H13035":"水源路中坑巷","H13036":"水源路北坑一巷","H13037":"水源路北坑巷","H13038":"水源路坪頂巷","H13039":"水源路南坑巷","H13040":"北陽一街","H13041":"北陽二街","H13042":"北陽三街","H13043":"北陽路","H13044":"市前街","H13045":"市政路","H13046":"民生街","H13047":"永安街","H13048":"永康路","H13049":"田心路１段","H13050":"田心路２段","H13051":"田心路２段二六七中巷","H13052":"田心路２段二六七東巷","H13053":"田心路２段二六七南巷","H13054":"同心街","H13055":"同安街","H13056":"向陽路","H13057":"合作街","H13058":"圳寮路","H13059":"圳寮路仁愛新村","H13060":"安和路","H13061":"安康路","H13062":"成功路","H13063":"朴子街","H13064":"自立街","H13065":"自成街","H13066":"自強南街","H13067":"自強街","H13068":"西平街","H13069":"西安街","H13070":"西勢一街","H13071":"西勢二街","H13072":"西勢三街","H13073":"西勢五街","H13074":"西勢六街","H13075":"西勢四街","H13076":"西勢路","H13077":"育才街","H13078":"育仁路","H13079":"育英路","H13080":"育德街","H13081":"角潭路１段","H13082":"角潭路２段","H13083":"協力街","H13084":"和平街","H13085":"府前街","H13086":"忠孝街","H13087":"明仁街","H13088":"明政街","H13089":"明義街","H13090":"明興街","H13091":"東仁街","H13092":"東北街","H13093":"東洲路","H13094":"東陽路","H13095":"東陽路山壽巷","H13096":"東陽路太坑巷","H13097":"東陽路秀坑巷","H13098":"東陽路泉州巷","H13099":"東陽路清谷巷","H13100":"東陽路獅座巷","H13101":"東陽路福德巷","H13102":"東陽路豪傑一巷","H13103":"東陽路豪傑二巷","H13104":"東勢街","H13105":"東興街","H13106":"直興街","H13107":"社皮路","H13108":"社興一街","H13109":"社興二街","H13110":"社興三街","H13111":"社興五街","H13112":"社興四街","H13113":"社興路","H13114":"長壽路","H13115":"長壽路北一巷","H13116":"長壽路北二巷","H13117":"長壽路北三巷","H13118":"長壽路南一巷","H13119":"長壽路南二巷","H13120":"長壽路南三巷","H13121":"長壽路南四巷","H13122":"信義街","H13123":"保康路","H13124":"南田街","H13125":"南村路","H13126":"南陽一街","H13127":"南陽路","H13128":"南陽路育樂新村","H13129":"南陽路南陽市場","H13130":"南陽路南陽新村","H13131":"南陽路國民新村","H13132":"南陽路逸仙莊","H13133":"南陽路綠山巷","H13134":"建成路","H13135":"師範街","H13136":"國豐路１段","H13137":"國豐路２段","H13138":"國豐路３段","H13139":"博愛街","H13140":"富春街","H13141":"富陽路","H13142":"復興路","H13143":"惠陽街","H13144":"朝陽路","H13145":"陽明街","H13146":"隆豐街","H13147":"圓環北路１段","H13148":"圓環北路２段","H13149":"圓環西路","H13150":"圓環東路","H13151":"圓環南路","H13152":"愛國街","H13153":"新生北路","H13154":"瑞安街","H13155":"瑞興路","H13156":"萬年路","H13157":"萬順一街","H13158":"萬順二街","H13159":"萬順三街","H13160":"葫蘆墩一街","H13161":"葫蘆墩二街","H13162":"葫蘆墩三街","H13163":"葫蘆墩五街","H13164":"葫蘆墩四街","H13165":"榮春街","H13166":"福德路","H13167":"綠山一街","H13168":"綠山二街","H13169":"綠山三街","H13170":"綠山五街","H13171":"綠山六街","H13172":"綠山四街","H13173":"樂天街","H13174":"興安街","H13175":"豐工路","H13176":"豐中路","H13177":"豐北街","H13178":"豐田路","H13179":"豐年路","H13180":"豐西街","H13181":"豐東一街","H13182":"豐東路","H13183":"豐社路","H13184":"豐社路芳泉巷","H13185":"豐南街","H13186":"豐洲路","H13187":"豐洲路中央巷","H13188":"豐原大道１段","H13189":"豐原大道１段五九五街","H13190":"豐原大道１段六七七街","H13191":"豐原大道１段六二五街","H13192":"豐原大道２段","H13193":"豐原大道３段","H13194":"豐原大道４段","H13195":"豐原大道４段三０三街","H13196":"豐原大道４段四三九街","H13197":"豐原大道５段","H13198":"豐原大道６段","H13199":"豐原大道７段","H13200":"豐原大道８段","H13201":"豐陽路","H13202":"豐勢路１段","H13203":"豐勢路２段","H13204":"雙龍街","H13205":"鎌村一街","H13206":"鎌村路","H13207":"寶山路"}