{"O13001":"力行巷","O13002":"三中路","O13003":"三民路","O13004":"大仁路","O13005":"大正街","O13006":"大吉路","O13007":"大同路","O13008":"大安街","O13009":"大成街","O13010":"大社工業區","O13011":"大社路","O13012":"大智街","O13013":"大順街","O13014":"大新路","O13015":"大聖街","O13016":"大德街","O13017":"大興街","O13018":"中山路","O13019":"中仁路","O13020":"中正路","O13021":"中華路","O13022":"中興一巷","O13023":"中興二巷","O13024":"中興三巷","O13025":"中興五巷","O13026":"中興四巷","O13027":"仁愛路","O13028":"文化路","O13029":"文和街","O13030":"文昌街","O13031":"文明路","O13032":"文信街","O13033":"文康街","O13034":"文華路","O13035":"文聖路","O13036":"文福街","O13037":"日新巷","O13038":"水哮巷","O13039":"北勢巷","O13040":"民生路","O13041":"民治路","O13042":"民族路","O13043":"民權路","O13044":"永宏巷","O13045":"永保街","O13046":"永華街","O13047":"田中巷","O13048":"田頂一巷","O13049":"田頂二巷","O13050":"田頂四巷","O13051":"光明街","O13052":"光華路","O13053":"安康街","O13054":"成功一巷","O13055":"成功二巷","O13056":"成功三巷","O13057":"成功六巷","O13058":"成功四巷","O13059":"自由路","O13060":"自強街","O13061":"行堂巷","O13062":"和平一巷","O13063":"和平二巷","O13064":"和平三巷","O13065":"和平五巷","O13066":"和平四巷","O13067":"和平路１段","O13068":"和平路２段","O13069":"和成街","O13070":"忠孝路","O13071":"明園巷","O13072":"明毅街","O13073":"金龍路","O13074":"信義路","O13075":"保舍甲路","O13076":"保糖街","O13077":"柑宅巷","O13078":"苗圃巷","O13079":"食坑巷","O13080":"神農路","O13081":"堂內巷","O13082":"桶寮巷","O13083":"復興路","O13084":"新生街","O13085":"新興路","O13086":"萬金巷","O13087":"萬金路","O13088":"經建路","O13089":"蜈潭巷","O13090":"過甲一巷","O13091":"過甲二巷","O13092":"過甲三巷","O13093":"過甲四巷","O13094":"嘉新巷","O13095":"嘉誠路","O13096":"壽山巷","O13097":"旗楠路","O13098":"翠屏路","O13099":"學府路","O13100":"磚廠街","O13101":"興工路","O13102":"鹽埕巷"}