{"O20001":"力行路","O20002":"下市場","O20003":"大山巷","O20004":"大仁路","O20005":"大占巷","O20006":"大成路","O20007":"大勇巷","O20008":"大埔巷","O20009":"大學路","O20010":"大遼路","O20011":"工程路","O20012":"中北路","O20013":"中民路","O20014":"中生巷","O20015":"中安路","O20016":"中竹路","O20017":"中西路","O20018":"中東巷","O20019":"中南路","O20020":"中華路","O20021":"中路巷","O20022":"中興北路","O20023":"中興路","O20024":"內湖巷","O20025":"北一路","O20026":"四林路","O20027":"市場路","O20028":"正德新村","O20029":"永興巷","O20030":"田尾巷","O20031":"石尖巷","O20032":"安中路","O20033":"安北路","O20034":"安正路","O20035":"安西路","O20036":"安招路","O20037":"安東街","O20038":"安林一街","O20039":"安林二街","O20040":"安林三街","O20041":"安林五街","O20042":"安林六街","O20043":"安林四街","O20044":"安林路","O20045":"安南二路","O20046":"安南路","O20047":"安新路","O20048":"安慶路","O20049":"尖山巷","O20050":"成大街","O20051":"成功路","O20052":"角宿路","O20053":"角宿路北巷","O20054":"車林巷","O20055":"和尚巷","O20056":"拖砧巷","O20057":"東川路","O20058":"林厝巷","O20059":"牧場路","O20060":"臥牛巷","O20061":"金山路","O20062":"南一巷","O20063":"南勢巷","O20064":"後角巷","O20065":"後荷巷","O20066":"後龍巷","O20067":"紅山巷","O20068":"迪化路","O20069":"師大路","O20070":"海成一街","O20071":"海成二街","O20072":"海成三街","O20073":"海成北街","O20074":"海成東街","O20075":"海成南街","O20076":"海成街","O20077":"海峰路","O20078":"烏山巷","O20079":"高鐵總廠路","O20080":"埤底巷","O20081":"崎溜巷","O20082":"深中路","O20083":"深水路","O20084":"深興路","O20085":"湖內巷","O20086":"番田路","O20087":"新生南路","O20088":"新生路","O20089":"新厝巷","O20090":"溪底巷","O20091":"義大路","O20092":"裕農巷","O20093":"過鞍巷","O20094":"滾水路","O20095":"鳳加路","O20096":"鳳西巷","O20097":"鳳東路","O20098":"鳳旗路","O20099":"鳳澄路","O20100":"鳳龍巷","O20101":"鞍平巷","O20102":"橫山路","O20103":"燕南二街","O20104":"燕南三街","O20105":"燕新一街","O20106":"燕新二街","O20107":"燕新三街","O20108":"燕新五街","O20109":"興隆巷","O20110":"興龍路","O20111":"瓊招路","O20112":"瓊林路","O20113":"瓊興路","O20114":"麒麟巷","O20115":"寶頂一街","O20116":"寶頂東街","O20117":"寶頂巷"}