{"P12001":"人和路","P12002":"八德路","P12003":"三和路","P12004":"上寧路","P12005":"上樹村北寧路","P12006":"大同路１段","P12007":"大同路２段","P12008":"大同路２段東興巷","P12009":"大同路２段南一巷","P12010":"大同路２段南二巷","P12011":"大同路２段福泉巷","P12012":"大同路３段","P12013":"大同路３段榮和巷","P12014":"大同路４段","P12015":"大同路４段東金巷","P12016":"大同路５段","P12017":"大旺路","P12018":"大明巷","P12019":"大茂巷","P12020":"大旋巷","P12021":"大博巷","P12022":"大發路","P12023":"大新路","P12024":"大新路大展巷","P12025":"大義路","P12026":"山水路","P12027":"中山路","P12028":"中央巷","P12029":"中正路","P12030":"中圳巷","P12031":"中林路","P12032":"中原巷","P12033":"中清巷","P12034":"中清橫巷","P12035":"中勝路","P12036":"中華一街","P12037":"中華二街","P12038":"中華三街","P12039":"中寧路","P12040":"中興路","P12041":"五經巷","P12042":"仁和路","P12043":"仁智路","P12044":"仁華路","P12045":"仁愛路","P12046":"內埔市場","P12047":"內埔村南華路","P12048":"太平巷","P12049":"文山路","P12050":"文化路","P12051":"文光巷","P12052":"文忠路","P12053":"文昌路","P12054":"文明巷","P12055":"文盛路","P12056":"水源路","P12057":"北平巷","P12058":"北寧路","P12059":"北寧路２段","P12060":"四份巷","P12061":"四維路","P12062":"平山路","P12063":"平昌街","P12064":"必勝路","P12065":"必發巷","P12066":"民生路","P12067":"民善路","P12068":"永平街","P12069":"永田路","P12070":"永光路","P12071":"永安巷","P12072":"永安路","P12073":"永定巷","P12074":"永昌巷","P12075":"永隆巷","P12076":"永新路","P12077":"永興二巷","P12078":"永興巷","P12079":"永豐巷","P12080":"光明巷","P12081":"光明路","P12082":"光復路","P12083":"光華街","P12084":"向北巷","P12085":"地利路","P12086":"安和巷","P12087":"成功路","P12088":"早角路","P12089":"竹山路","P12090":"竹北巷","P12091":"竹西巷","P12092":"竹東路","P12093":"竹南路","P12094":"竹興路","P12095":"竹豐巷","P12096":"自力路","P12097":"自立路","P12098":"自強路","P12099":"西平路","P12100":"西圳巷","P12101":"西安巷","P12102":"西安路","P12103":"西淇路","P12104":"西銀東巷","P12105":"西銀巷","P12106":"利寧路","P12107":"汾陽一巷","P12108":"汾陽二巷","P12109":"汾陽三巷","P12110":"育文路","P12111":"育英路","P12112":"里仁路","P12113":"里北路","P12114":"里和路","P12115":"里東路","P12116":"里信路","P12117":"里南路","P12118":"里智路","P12119":"里順路","P12120":"里新路","P12121":"里義路","P12122":"和仁路","P12123":"和平新路","P12124":"和平路","P12125":"和光路","P12126":"和成巷","P12127":"和美路","P12128":"和順路","P12129":"和寧路","P12130":"和興路","P12131":"延平路","P12132":"忠孝路","P12133":"忠英路","P12134":"忠義路","P12135":"昌宏路","P12136":"昌南路","P12137":"明東路","P12138":"明華路","P12139":"明德路","P12140":"昇平街","P12141":"昇華路","P12142":"東山巷","P12143":"東川路","P12144":"東平巷","P12145":"東圳巷","P12146":"東成路","P12147":"東陽街","P12148":"東寧路","P12149":"東興路","P12150":"河南巷","P12151":"金陵路","P12152":"長青巷","P12153":"信東路","P12154":"信義路","P12155":"信寧路","P12156":"信興巷","P12157":"南山路","P12158":"南平一巷","P12159":"南平巷","P12160":"南平路","P12161":"南華路成邦新莊","P12162":"南寧路","P12163":"南豐路","P12164":"屏光路","P12165":"建三路","P12166":"建工路","P12167":"建中巷","P12168":"建文路","P12169":"建平路","P12170":"建民路","P12171":"建邦路","P12172":"建和路","P12173":"建明路","P12174":"建國路","P12175":"建康巷","P12176":"建富路","P12177":"建華路","P12178":"建新路","P12179":"建業路","P12180":"建興村","P12181":"建興村榮華巷","P12182":"建興路","P12183":"後廟巷","P12184":"昭勝路","P12185":"昭勝路安平一巷","P12186":"昭勝路安平二巷","P12187":"昭勝路安平三巷","P12188":"昭勝路安平五巷","P12189":"昭勝路安平四巷","P12190":"科大北路","P12191":"科大路１段","P12192":"科大路２段","P12193":"科大路３段","P12194":"美興路","P12195":"茄苳路","P12196":"原勝路","P12197":"唐華路","P12198":"埔興路","P12199":"展興路","P12200":"振興路","P12201":"振豐村榮華巷","P12202":"桑原巷","P12203":"海平路","P12204":"埤頭巷","P12205":"崇文巷","P12206":"崇聖路","P12207":"康寧路","P12208":"清涼路１段","P12209":"清涼路１段二九０橫巷","P12210":"清涼路２段","P12211":"清華路","P12212":"統嶺巷","P12213":"通安路","P12214":"通賢巷","P12215":"通霄巷","P12216":"勝光路","P12217":"勝利路","P12218":"博愛巷","P12219":"富貴巷","P12220":"富豐路","P12221":"復興巷","P12222":"復興路","P12223":"惠陽街","P12224":"朝陽巷","P12225":"善化路","P12226":"華光巷","P12227":"華安路","P12228":"華成巷","P12229":"陽明路","P12230":"陽濟路","P12231":"勤英路","P12232":"新中路","P12233":"新生路","P12234":"新生路榮和巷","P12235":"新田路","P12236":"新光路","P12237":"新東路","P12238":"新南路","P12239":"新唐路","P12240":"新展路","P12241":"新勝路","P12242":"新發路","P12243":"新興路","P12244":"新豐北路","P12245":"新豐路","P12246":"溝背巷","P12247":"瑞華路","P12248":"瑞穗路","P12249":"綏平路","P12250":"農專街","P12251":"嘉應路","P12252":"嘉應路北一巷","P12253":"嘉應路北二巷","P12254":"嘉應路北三巷","P12255":"嘉應路西巷","P12256":"嘉應路南巷","P12257":"壽比路","P12258":"壽埤巷","P12259":"福原路","P12260":"福泰路","P12261":"福壽路","P12262":"福寧路","P12263":"福德路","P12264":"廣田路","P12265":"廣濟路","P12266":"德光巷","P12267":"德美路","P12268":"德修路","P12269":"樂平街","P12270":"黎和巷","P12271":"黎東路","P12272":"學人路","P12273":"學成街","P12274":"學府路","P12275":"學興路","P12276":"樹山路","P12277":"樹山路樹田巷","P12278":"樹山路樹寧巷","P12279":"樹山路樹德巷","P12280":"樹新路","P12281":"興中一巷","P12282":"興中二巷","P12283":"興中三巷","P12284":"興南村南華路","P12285":"興南路","P12286":"興華路","P12287":"興義路","P12288":"遼北路","P12289":"龍美路","P12290":"龍真路","P12291":"龍崗路","P12292":"龍勝路","P12293":"龍善路","P12294":"龍鳳路","P12295":"龍德路","P12296":"龍興路","P12297":"龍灣巷","P12298":"環山路","P12299":"聯通街","P12300":"懷忠路","P12301":"瀧觀巷","P12302":"觀山街"}