{"R13001":"三台","R13002":"大莊路","R13003":"中山路","R13004":"中興路","R13005":"六十石山","R13006":"公界街","R13007":"公埔路","R13008":"公埔路２段","R13009":"文化路","R13010":"四維","R13011":"民權路","R13012":"永安街","R13013":"永豐","R13014":"永豐村復興","R13015":"石牌","R13016":"光明路","R13017":"后庄路","R13018":"安通","R13019":"安靜街","R13020":"吳江","R13021":"車站街","R13022":"車站街１段","R13023":"和平街","R13024":"明里","R13025":"東竹","R13026":"東里村復興","R13027":"東昇路","R13028":"東湖","R13029":"東寧","R13030":"東興","R13031":"南興路","R13032":"草坪","R13033":"清坑","R13034":"富北","R13035":"富田","R13036":"富南","R13037":"富豐路","R13038":"復興路","R13039":"朝寧","R13040":"湧泉路","R13041":"雲閩","R13042":"新莊","R13043":"新富","R13044":"新興","R13045":"源和","R13046":"萬寧","R13047":"道化路","R13048":"福安路","R13049":"福崗","R13050":"廣興路","R13051":"慶光路","R13052":"學富路","R13053":"豐南","R13054":"豐南村復興","R13055":"鎮寧","R13056":"羅山"}